package Graphics;

import javax.microedition.lcdui.Graphics;

public final class bb extends m {
  public bb(GraphicParent paramcb, byte[] paramArrayOfbyte) {
    super(paramcb, paramArrayOfbyte, (byte)0, bp.a.a(18));
  }
  
  public final boolean a(int paramInt1, int paramInt2) {
    // Byte code:
    //   0: aload_0
    //   1: iload_1
    //   2: iload_2
    //   3: invokevirtual b : (II)Z
    //   6: ifeq -> 11
    //   9: iconst_1
    //   10: ireturn
    //   11: aload_0
    //   12: iload_1
    //   13: iload_2
    //   14: invokevirtual c : (II)Z
    //   17: ifeq -> 22
    //   20: iconst_1
    //   21: ireturn
    //   22: iload_2
    //   23: bipush #53
    //   25: if_icmpeq -> 34
    //   28: iload_1
    //   29: bipush #8
    //   31: if_icmpne -> 111
    //   34: invokestatic a : ()Lao;
    //   37: getfield a : Lg;
    //   40: aload_0
    //   41: getfield h : [B
    //   44: aload_0
    //   45: getfield b : B
    //   48: baload
    //   49: invokevirtual a : (I)Lad;
    //   52: dup
    //   53: astore_3
    //   54: invokevirtual b : ()Z
    //   57: ifeq -> 95
    //   60: aload_0
    //   61: iconst_1
    //   62: iconst_0
    //   63: iconst_2
    //   64: anewarray java/lang/Object
    //   67: dup
    //   68: iconst_0
    //   69: getstatic bp.a : Lz;
    //   72: bipush #19
    //   74: invokevirtual a : (I)[C
    //   77: aastore
    //   78: dup
    //   79: iconst_1
    //   80: getstatic bp.a : Lz;
    //   83: bipush #20
    //   85: invokevirtual a : (I)[C
    //   88: aastore
    //   89: invokevirtual a : (BB[Ljava/lang/Object;)V
    //   92: goto -> 109
    //   95: aload_0
    //   96: new ab
    //   99: dup
    //   100: aload_0
    //   101: aload_3
    //   102: iconst_0
    //   103: invokespecial <init> : (Lcb;Lad;Z)V
    //   106: putfield b : Lcb;
    //   109: iconst_1
    //   110: ireturn
    //   111: iload_2
    //   112: bipush #-8
    //   114: if_icmpeq -> 123
    //   117: iload_2
    //   118: bipush #35
    //   120: if_icmpne -> 134
    //   123: aload_0
    //   124: getfield a : Lcb;
    //   127: iconst_m1
    //   128: iconst_m1
    //   129: invokevirtual a : (BB)V
    //   132: iconst_1
    //   133: ireturn
    //   134: iconst_1
    //   135: ireturn
  }
  
  public final void a(byte paramByte1, byte paramByte2) {
    // Byte code:
    //   0: aload_0
    //   1: getfield b : Lcb;
    //   4: astore_3
    //   5: aload_0
    //   6: iload_1
    //   7: iload_2
    //   8: invokespecial a : (BB)V
    //   11: aload_3
    //   12: instanceof ab
    //   15: ifeq -> 97
    //   18: aload_0
    //   19: getfield a : Lcb;
    //   22: invokevirtual a : ()V
    //   25: invokestatic a : ()Lao;
    //   28: getfield a : Lg;
    //   31: invokevirtual a : ()[B
    //   34: dup
    //   35: astore #4
    //   37: arraylength
    //   38: ifle -> 62
    //   41: aload_0
    //   42: getfield a : Lcb;
    //   45: new bb
    //   48: dup
    //   49: aload_0
    //   50: getfield a : Lcb;
    //   53: aload #4
    //   55: invokespecial <init> : (Lcb;[B)V
    //   58: putfield b : Lcb;
    //   61: return
    //   62: aload_0
    //   63: getfield a : Lcb;
    //   66: iconst_1
    //   67: iconst_0
    //   68: iconst_2
    //   69: anewarray java/lang/Object
    //   72: dup
    //   73: iconst_0
    //   74: getstatic bp.a : Lz;
    //   77: bipush #21
    //   79: invokevirtual a : (I)[C
    //   82: aastore
    //   83: dup
    //   84: iconst_1
    //   85: getstatic bp.a : Lz;
    //   88: bipush #22
    //   90: invokevirtual a : (I)[C
    //   93: aastore
    //   94: invokevirtual a : (BB[Ljava/lang/Object;)V
    //   97: return
  }
  
  public final void a(Graphics paramGraphics, int paramInt1, int paramInt2) {
    bh.a(paramGraphics);
    bh.a(paramGraphics, bh.i, (char[])bh.e);
    super.a(paramGraphics, paramInt1, paramInt2);
    paramGraphics.drawImage(ce.b, bp.a + 155 - 38, bp.b + 170 - 22, 20);
  }
}


/* Location:              /home/markes/Downloads/wind_of_soltia/!/bb.class
 * Java compiler version: 1 (45.3)
 * JD-Core Version:       1.1.3
 */