package Graphics;

import javax.microedition.lcdui.Graphics;

public final class be extends GraphicParent {
  private boolean c;
  
  private bs a;
  
  public be(GraphicParent paramcb, boolean paramBoolean) {
    super(paramcb, (byte)4);
    this.c = paramBoolean;
    this.a = bs.a;
  }
  
  public final boolean a(int paramInt1, int paramInt2) {
    // Byte code:
    //   0: aload_0
    //   1: iload_1
    //   2: iload_2
    //   3: invokevirtual b : (II)Z
    //   6: ifeq -> 11
    //   9: iconst_1
    //   10: ireturn
    //   11: aload_0
    //   12: iload_1
    //   13: iload_2
    //   14: iconst_0
    //   15: invokevirtual a : (IIZ)Z
    //   18: ifeq -> 23
    //   21: iconst_1
    //   22: ireturn
    //   23: iload_2
    //   24: bipush #52
    //   26: if_icmpeq -> 45
    //   29: iload_1
    //   30: iconst_2
    //   31: if_icmpeq -> 45
    //   34: iload_2
    //   35: bipush #54
    //   37: if_icmpeq -> 45
    //   40: iload_1
    //   41: iconst_5
    //   42: if_icmpne -> 300
    //   45: aload_0
    //   46: getfield b : B
    //   49: tableswitch default -> 300, 0 -> 80, 1 -> 149, 2 -> 253, 3 -> 278
    //   80: iload_2
    //   81: bipush #52
    //   83: if_icmpeq -> 91
    //   86: iload_1
    //   87: iconst_2
    //   88: if_icmpne -> 102
    //   91: aload_0
    //   92: getfield a : Lbs;
    //   95: iconst_0
    //   96: putfield a : I
    //   99: goto -> 123
    //   102: iload_2
    //   103: bipush #54
    //   105: if_icmpeq -> 113
    //   108: iload_1
    //   109: iconst_5
    //   110: if_icmpne -> 123
    //   113: aload_0
    //   114: getfield a : Lbs;
    //   117: getstatic bw.a : I
    //   120: putfield a : I
    //   123: aload_0
    //   124: getfield a : Lbs;
    //   127: getfield a : I
    //   130: invokestatic a : (I)V
    //   133: aload_0
    //   134: getfield a : Lbs;
    //   137: getfield a : I
    //   140: ifne -> 300
    //   143: invokestatic d : ()V
    //   146: goto -> 300
    //   149: iload_2
    //   150: bipush #52
    //   152: if_icmpeq -> 160
    //   155: iload_1
    //   156: iconst_2
    //   157: if_icmpne -> 192
    //   160: aload_0
    //   161: getfield a : Lbs;
    //   164: dup
    //   165: getfield a : B
    //   168: iconst_1
    //   169: isub
    //   170: i2b
    //   171: putfield a : B
    //   174: aload_0
    //   175: getfield a : Lbs;
    //   178: getfield a : B
    //   181: ifge -> 192
    //   184: aload_0
    //   185: getfield a : Lbs;
    //   188: iconst_2
    //   189: putfield a : B
    //   192: iload_2
    //   193: bipush #54
    //   195: if_icmpeq -> 203
    //   198: iload_1
    //   199: iconst_5
    //   200: if_icmpne -> 236
    //   203: aload_0
    //   204: getfield a : Lbs;
    //   207: dup
    //   208: getfield a : B
    //   211: iconst_1
    //   212: iadd
    //   213: i2b
    //   214: putfield a : B
    //   217: aload_0
    //   218: getfield a : Lbs;
    //   221: getfield a : B
    //   224: iconst_2
    //   225: if_icmple -> 236
    //   228: aload_0
    //   229: getfield a : Lbs;
    //   232: iconst_0
    //   233: putfield a : B
    //   236: aload_0
    //   237: getfield a : Lbs;
    //   240: aload_0
    //   241: getfield a : Lbs;
    //   244: getfield a : B
    //   247: invokevirtual a : (B)V
    //   250: goto -> 300
    //   253: aload_0
    //   254: getfield a : Lbs;
    //   257: aload_0
    //   258: getfield a : Lbs;
    //   261: getfield c : Z
    //   264: ifne -> 271
    //   267: iconst_1
    //   268: goto -> 272
    //   271: iconst_0
    //   272: putfield c : Z
    //   275: goto -> 300
    //   278: aload_0
    //   279: getfield a : Lbs;
    //   282: aload_0
    //   283: getfield a : Lbs;
    //   286: getfield d : Z
    //   289: ifne -> 296
    //   292: iconst_1
    //   293: goto -> 297
    //   296: iconst_0
    //   297: putfield d : Z
    //   300: iload_2
    //   301: bipush #-8
    //   303: if_icmpne -> 351
    //   306: aload_0
    //   307: getfield a : Lbs;
    //   310: getfield d : Z
    //   313: ifeq -> 328
    //   316: getstatic n.a : I
    //   319: putstatic n.c : I
    //   322: getstatic n.b : I
    //   325: putstatic n.d : I
    //   328: getstatic bs.a : Lbs;
    //   331: invokevirtual i : ()V
    //   334: goto -> 342
    //   337: dup
    //   338: astore_3
    //   339: invokevirtual printStackTrace : ()V
    //   342: aload_0
    //   343: getfield a : Lcb;
    //   346: invokevirtual a : ()V
    //   349: iconst_1
    //   350: ireturn
    //   351: iconst_1
    //   352: ireturn
    // Exception table:
    //   from	to	target	type
    //   328	334	337	java/lang/Exception
  }
  
  public final void a(Graphics paramGraphics, int paramInt1, int paramInt2) {
    int i = 0;
    int j = 0;
    if (this.c) {
      paramInt1 += 6;
      paramInt2 += 25;
      GraphicParent.a(paramGraphics, paramInt1, paramInt2, 143, 139);
      b(paramGraphics, paramInt1, paramInt2, 143, 139);
      i = 10452799;
      j = 16777215;
      paramInt1 += 5;
      paramInt2 += 15;
      bh.a(paramGraphics, bh.m, (char[])bh.e);
      paramInt1 += 15;
      paramInt2 += 10;
    } else {
      paramGraphics.setColor(4136767);
      paramGraphics.fillRect(0, 0, r.g, r.h);
      bf.c(paramGraphics, paramInt1, paramInt2);
      bh.a(paramGraphics, 5, paramInt1 + 155 >> 1, paramInt2 + 5);
      bf.b(paramGraphics, paramInt1, paramInt2 + 24, 3);
      paramInt1 += 15;
      paramInt2 += 10;
      paramInt1 += 12;
      paramInt2 += 46;
      paramGraphics.drawImage(ce.l[19], paramInt1 + 1, paramInt2 + 16, 20);
      paramGraphics.drawImage(ce.l[19], paramInt1 + 1, paramInt2 + 36, 20);
      paramGraphics.drawImage(ce.l[19], paramInt1 + 1, paramInt2 + 56, 20);
      bh.a(paramGraphics, (char[])null, (char[])bh.e);
    } 
    int k = paramInt2;
    byte b = this.b;
    paramGraphics.setColor((b == 0) ? 16777215 : i);
    bh.a(paramGraphics, paramInt1, k, ce.g.a(18), 1);
    paramGraphics.setColor(j);
    if (this.a.a == null) {
      bh.a(paramGraphics, paramInt1 + 70, k, cj.a.a(3945).toCharArray(), 0);
    } else {
      bh.a(paramGraphics, paramInt1 + 70, k, cj.a.a(3944).toCharArray(), 0);
    } 
    k += 20;
    paramGraphics.setColor((b == 1) ? 16777215 : i);
    bh.a(paramGraphics, paramInt1, k, ce.g.a(19), 1);
    paramGraphics.setColor(j);
    char[] arrayOfChar = ce.g.a(60 + this.a.a);
    bh.a(paramGraphics, paramInt1 + 70, k, arrayOfChar, 0);
    k += 20;
    paramGraphics.setColor((b == 2) ? 16777215 : i);
    bh.a(paramGraphics, paramInt1, k, ce.g.a(20), 1);
    paramGraphics.setColor(j);
    bh.a(paramGraphics, paramInt1 + 70, k, (this.a.c ? cj.a.a(3942) : cj.a.a(3943)).toCharArray(), 0);
    k += 20;
    paramGraphics.setColor((b == 3) ? 16777215 : i);
    bh.a(paramGraphics, paramInt1, k, ce.g.a(21), 1);
    paramGraphics.setColor(j);
    bh.a(paramGraphics, paramInt1 + 70, k, (this.a.d ? cj.a.a(3944) : cj.a.a(3945)).toCharArray(), 0);
    byte b1;
    for (b1 = 0; b1 < super.a; b1 = (byte)(b1 + 1)) {
      paramGraphics.drawImage(ce.o, paramInt1 + 42, paramInt2 + b1 * 20, 20);
      paramGraphics.drawImage(ce.d, paramInt1 + 92, paramInt2 + b1 * 20, 20);
    } 
  }
}


/* Location:              /home/markes/Downloads/wind_of_soltia/!/be.class
 * Java compiler version: 1 (45.3)
 * JD-Core Version:       1.1.3
 */