package Graphics;

import java.io.IOException;

public final class z {
  private int[] a;
  
  public short a;
  
  public z(String paramString) throws IOException {
    // Byte code:
    //   0: aload_0
    //   1: invokespecial <init> : ()V
    //   4: new java/lang/StringBuffer
    //   7: dup
    //   8: invokespecial <init> : ()V
    //   11: aload_1
    //   12: invokevirtual append : (Ljava/lang/String;)Ljava/lang/StringBuffer;
    //   15: ldc '.tdf'
    //   17: invokevirtual append : (Ljava/lang/String;)Ljava/lang/StringBuffer;
    //   20: invokevirtual toString : ()Ljava/lang/String;
    //   23: invokestatic a : (Ljava/lang/String;)[B
    //   26: astore_2
    //   27: iconst_0
    //   28: istore_3
    //   29: aload_0
    //   30: aload_2
    //   31: iconst_0
    //   32: iinc #3, 1
    //   35: baload
    //   36: sipush #255
    //   39: iand
    //   40: i2s
    //   41: putfield a : S
    //   44: aload_0
    //   45: aload_0
    //   46: getfield a : S
    //   49: newarray int
    //   51: putfield a : [I
    //   54: iconst_0
    //   55: istore #5
    //   57: iload #5
    //   59: aload_0
    //   60: getfield a : S
    //   63: if_icmpge -> 134
    //   66: aload_2
    //   67: iload_3
    //   68: iinc #3, 1
    //   71: baload
    //   72: sipush #255
    //   75: iand
    //   76: bipush #8
    //   78: ishl
    //   79: dup
    //   80: istore #4
    //   82: aload_2
    //   83: iload_3
    //   84: iinc #3, 1
    //   87: baload
    //   88: sipush #255
    //   91: iand
    //   92: iadd
    //   93: istore #4
    //   95: new java/lang/String
    //   98: dup
    //   99: aload_2
    //   100: iload_3
    //   101: iload #4
    //   103: invokespecial <init> : ([BII)V
    //   106: astore #6
    //   108: aload_0
    //   109: getfield a : [I
    //   112: iload #5
    //   114: aload #6
    //   116: invokevirtual trim : ()Ljava/lang/String;
    //   119: invokestatic parseInt : (Ljava/lang/String;)I
    //   122: iastore
    //   123: iload_3
    //   124: iload #4
    //   126: iadd
    //   127: istore_3
    //   128: iinc #5, 1
    //   131: goto -> 57
    //   134: return
  }
  
  public final char[] a(int paramInt) {
    return cj.a.a(this.a[paramInt]).replace(';', '\n').toCharArray();
  }
}


/* Location:              /home/markes/Downloads/wind_of_soltia/!/z.class
 * Java compiler version: 1 (45.3)
 * JD-Core Version:       1.1.3
 */