import java.awt.Graphics;
import java.awt.Image;

public abstract class GraphicParent implements u {
  public GraphicParent cb_a;
  
  public GraphicParent cb_b;
  
  private boolean b;
  
  public boolean a;
  
  public byte byte_a;
  
  public byte byte_b;
  
  public GraphicParent(GraphicParent paramcb, byte paramByte) {
    this.cb_a = paramcb;
    this.cb_b = null;
    this.b = true;
    this.a = true;
    this.byte_a = paramByte;
    this.byte_b = 0;
  }
  
  public abstract boolean get_a(int paramInt1, int paramInt2);
  
  public final boolean get_b(int paramInt1, int paramInt2) {
    // Byte code:
    //   0: aload_0
    //   1: getfield b : Lcb;
    //   4: ifnull -> 21
    //   7: aload_0
    //   8: getfield b : Lcb;
    //   11: iload_1
    //   12: iload_2
    //   13: invokevirtual a : (II)Z
    //   16: ifeq -> 21
    //   19: iconst_1
    //   20: ireturn
    //   21: aload_0
    //   22: iconst_1
    //   23: putfield a : Z
    //   26: iconst_0
    //   27: ireturn
    return false;
  };
  
  public abstract void set_a(Graphics paramGraphics, int paramInt1, int paramInt2);
  
  public final void b(Graphics paramGraphics, int paramInt1, int paramInt2) {
    // Byte code:
    //   0: iconst_0
    //   1: istore #4
    //   3: aload_0
    //   4: getfield a : Z
    //   7: ifeq -> 25
    //   10: aload_0
    //   11: iconst_0
    //   12: putfield a : Z
    //   15: aload_0
    //   16: aload_1
    //   17: iload_2
    //   18: iload_3
    //   19: invokevirtual a : (Ljavax/microedition/lcdui/Graphics;II)V
    //   22: iconst_1
    //   23: istore #4
    //   25: aload_0
    //   26: getfield b : Lcb;
    //   29: ifnonnull -> 57
    //   32: aload_0
    //   33: getfield b : Z
    //   36: ifeq -> 67
    //   39: iload #4
    //   41: ifne -> 51
    //   44: aload_0
    //   45: aload_1
    //   46: iload_2
    //   47: iload_3
    //   48: invokevirtual a : (Ljavax/microedition/lcdui/Graphics;II)V
    //   51: aload_0
    //   52: iconst_0
    //   53: putfield b : Z
    //   56: return
    //   57: aload_0
    //   58: getfield b : Lcb;
    //   61: aload_1
    //   62: iload_2
    //   63: iload_3
    //   64: invokevirtual b : (Ljavax/microedition/lcdui/Graphics;II)V
    //   67: return
  }
  
  public final boolean a(int paramInt1, int paramInt2, boolean paramBoolean) {
    switch (paramInt2) {
      case 50:
        a((byte)3, paramBoolean);
        return true;
      case 56:
        a((byte)4, paramBoolean);
        return true;
    } 
    switch (paramInt1) {
      case 1:
        a((byte)3, paramBoolean);
        return true;
      case 6:
        a((byte)4, paramBoolean);
        return true;
    } 
    return false;
  }
  
  public final boolean c(int paramInt1, int paramInt2) {
    return a(paramInt1, paramInt2, false);
  }
  
  public final boolean d(int paramInt1, int paramInt2) {
    switch (paramInt2) {
      case 52:
        a((byte)3);
        return true;
      case 54:
        a((byte)4);
        return true;
    } 
    switch (paramInt1) {
      case 2:
        a((byte)3);
        return true;
      case 5:
        a((byte)4);
        return true;
    } 
    return false;
  }
  
  public void a(byte paramByte) {
    a(paramByte, true);
  }
  
  public final void a(byte paramByte, boolean paramBoolean) {
    if (paramByte == 4) {
      this.b = (byte)(this.b + 1);
      if (this.b >= this.a) {
        if (paramBoolean) {
          this.b = 0;
          return;
        } 
        this.b = (byte)(this.a - 1);
        if (this.b < 0) {
          this.b = 0;
          return;
        } 
      } 
    } else {
      this.b = (byte)(this.b - 1);
      if (this.b < 0) {
        if (paramBoolean) {
          this.b = (byte)(this.a - 1);
          return;
        } 
        this.b = 0;
      } 
    } 
  }
  
  public void a(byte paramByte1, byte paramByte2) {
    this.b = null;
    if (bs.a != null)
      bs.a.a(); 
    b();
  }
  
  public final void a() {
    this.b = null;
    if (bs.a != null)
      bs.a.a(); 
    b();
  }
  
  public final void a(byte paramByte1, byte paramByte2, Object[] paramArrayOfObject) {
    this.b = new af(this, paramByte1, paramByte2, paramArrayOfObject, null, null);
  }
  
  public final void a(byte paramByte1, byte paramByte2, Object[] paramArrayOfObject, char[] paramArrayOfchar1, char[] paramArrayOfchar2) {
    this.b = new af(this, paramByte1, paramByte2, paramArrayOfObject, paramArrayOfchar1, paramArrayOfchar2);
  }
  
  public final void a(Object[] paramArrayOfObject) {
    this.b = new af(this, (byte)1, (byte)0, paramArrayOfObject, null, null);
  }
  
  public final void b() {
    // Byte code:
    //   0: aload_0
    //   1: getfield a : Lcb;
    //   4: ifnull -> 14
    //   7: aload_0
    //   8: getfield a : Lcb;
    //   11: invokevirtual b : ()V
    //   14: aload_0
    //   15: iconst_1
    //   16: putfield a : Z
    //   19: return
  }
  
  public final void c() {
    // Byte code:
    //   0: aload_0
    //   1: getfield b : Lcb;
    //   4: ifnull -> 14
    //   7: aload_0
    //   8: getfield b : Lcb;
    //   11: invokevirtual c : ()V
    //   14: aload_0
    //   15: iconst_1
    //   16: putfield a : Z
    //   19: return
  }
  
  public final int a() {
    return this.b / 5 + 1;
  }
  
  public final int b() {
    return (this.a - 1) / 5 + 1;
  }
  
  public final int c() {
    return (a() - 1) * 5;
  }
  
  public final int d() {
    int i;
    return ((i = a() * 5 - 1) > this.a - 1) ? (this.a - 1) : i;
  }
  
  public final void a(Graphics paramGraphics, int paramInt1, int paramInt2, boolean paramBoolean) {
    byte b = (byte)(this.b % 5);
    int i;
    if ((i = this.a - (a() - 1) * 5) > 5)
      i = 5; 
    byte b1;
    for (b1 = 0; b1 < i; b1 = (byte)(b1 + 1)) {
      if (b1 != b)
        a(paramGraphics, paramInt1, paramInt2, b1, false); 
    } 
    a(paramGraphics, paramInt1 + 27, paramInt2 + 10, 120, 137, 4136767, 10452799, 4144959);
    a(paramGraphics, paramInt1 + 27, paramInt2 + 10, 120, 137, 6242111);
    a(paramGraphics, paramInt1, paramInt2, b, true);
    if (paramBoolean) {
      if (a() > 1)
        paramGraphics.drawImage(ce.k, paramInt1 + 70, paramInt2 + 4, 20); 
      if (a() < b())
        paramGraphics.drawImage((Image)ce.n, paramInt1 + 70, paramInt2 + 148, 20); 
    } 
  }
  
  private static final void a(Graphics paramGraphics, int paramInt1, int paramInt2, int paramInt3, int paramInt4, int paramInt5, int paramInt6) {
    paramGraphics.setColor(paramInt5);
    paramGraphics.drawLine(paramInt1 + 1, paramInt2, paramInt1 + paramInt3 - 2, paramInt2);
    paramGraphics.drawLine(paramInt1, paramInt2 + 1, paramInt1, paramInt2 + paramInt4 - 2);
    paramGraphics.setColor(paramInt6);
    paramGraphics.drawLine(paramInt1 + paramInt3 - 1, paramInt2 + 1, paramInt1 + paramInt3 - 1, paramInt2 + paramInt4 - 1);
    paramGraphics.drawLine(paramInt1 + 1, paramInt2 + paramInt4 - 1, paramInt1 + paramInt3 - 2, paramInt2 + paramInt4 - 1);
  }
  
  private static final void c(Graphics paramGraphics, int paramInt1, int paramInt2, int paramInt3, int paramInt4, int paramInt5) {
    paramGraphics.setColor(paramInt5);
    paramGraphics.fillRect(paramInt1 + 1, paramInt2 + 1, paramInt3 - 2, paramInt4 - 2);
  }
  
  public static final void a(Graphics paramGraphics, int paramInt1, int paramInt2, int paramInt3, int paramInt4, int paramInt5, int paramInt6, int paramInt7) {
    paramGraphics.setColor(paramInt5);
    paramGraphics.drawLine(paramInt1 + 1, paramInt2, paramInt1 + paramInt3 - 2, paramInt2);
    paramGraphics.drawLine(paramInt1 + paramInt3 - 1, paramInt2 + 1, paramInt1 + paramInt3 - 1, paramInt2 + paramInt4 - 2);
    paramGraphics.drawLine(paramInt1 + 1, paramInt2 + paramInt4 - 1, paramInt1 + paramInt3 - 2, paramInt2 + paramInt4 - 1);
    paramGraphics.drawLine(paramInt1, paramInt2 + 1, paramInt1, paramInt2 + paramInt4 - 2);
    paramGraphics.setColor(paramInt6);
    paramGraphics.drawLine(paramInt1 + 1, paramInt2 + 1, paramInt1 + paramInt3 - 3, paramInt2 + 1);
    paramGraphics.drawLine(paramInt1 + 1, paramInt2 + 1, paramInt1 + 1, paramInt2 + paramInt4 - 3);
    paramGraphics.setColor(paramInt7);
    paramGraphics.drawLine(paramInt1 + paramInt3 - 2, paramInt2 + 1, paramInt1 + paramInt3 - 2, paramInt2 + paramInt4 - 3);
    paramGraphics.drawLine(paramInt1 + 1, paramInt2 + paramInt4 - 2, paramInt1 + paramInt3 - 2, paramInt2 + paramInt4 - 2);
  }
  
  public static final void a(Graphics paramGraphics, int paramInt1, int paramInt2, int paramInt3, int paramInt4, int paramInt5) {
    paramGraphics.setColor(paramInt5);
    paramGraphics.fillRect(paramInt1 + 2, paramInt2 + 2, paramInt3 - 4, paramInt4 - 4);
  }
  
  public static final void b(Graphics paramGraphics, int paramInt1, int paramInt2, int paramInt3, int paramInt4, int paramInt5) {
    paramGraphics.setColor(paramInt5);
    paramGraphics.drawLine(paramInt1 + 1, paramInt2, paramInt1 + paramInt3 - 2, paramInt2);
    paramGraphics.drawLine(paramInt1, paramInt2 + 1, paramInt1, paramInt2 + paramInt4 - 2);
    paramGraphics.drawLine(paramInt1 + paramInt3 - 1, paramInt2 + 1, paramInt1 + paramInt3 - 1, paramInt2 + paramInt4 - 2);
    paramGraphics.drawLine(paramInt1 + 1, paramInt2 + paramInt4 - 1, paramInt1 + paramInt3 - 2, paramInt2 + paramInt4 - 1);
    paramGraphics.fillRect(paramInt1 + 1, paramInt2 + 1, paramInt3 - 2, paramInt4 - 2);
  }
  
  public static final void a(Graphics paramGraphics, int paramInt1, int paramInt2, int paramInt3, int paramInt4) {
    a(paramGraphics, paramInt1, paramInt2, paramInt3, paramInt4, 2039615, 6242111, 2039615);
  }
  
  public static final void b(Graphics paramGraphics, int paramInt1, int paramInt2, int paramInt3, int paramInt4) {
    a(paramGraphics, paramInt1, paramInt2, paramInt3, paramInt4, 4136767);
  }
  
  public static final void a(Graphics paramGraphics, int paramInt1, int paramInt2, byte paramByte, boolean paramBoolean) {
    int i = paramInt1 + 3;
    int j = paramInt2 + 10 + paramByte * 23;
    paramGraphics.setColor(paramBoolean ? 4136767 : 6242111);
    paramGraphics.fillRect(i + 1, j, 24, 1);
    paramGraphics.fillRect(i, j + 1, 1, 16);
    paramGraphics.fillRect(i + 1, j + 17, 24, 1);
    paramGraphics.setColor(paramBoolean ? 10452799 : 14663551);
    paramGraphics.fillRect(i + 1, j + 1, 24, 1);
    paramGraphics.fillRect(i + 1, j + 1, 1, 16);
    paramGraphics.setColor(paramBoolean ? 4144959 : 8347519);
    paramGraphics.fillRect(i + 2, j + 16, 23, 1);
    paramGraphics.setColor(paramBoolean ? 6242111 : 10452863);
    paramGraphics.fillRect(i + 2, j + 2, 24, 14);
  }
  
  public static final void a(Graphics paramGraphics, int paramInt1, int paramInt2, int paramInt3) {
    r.c(paramGraphics, paramInt3, paramInt1, paramInt2, 8);
    int i = r.a(paramInt3);
    paramGraphics.drawImage((Image)ce.m, paramInt1 - i, paramInt2, 24);
  }
  
  public static final void a(Graphics paramGraphics, int paramInt1, int paramInt2, ad paramad, boolean paramBoolean) {
    paramGraphics.drawImage(ce.d[paramad.f], paramInt1, paramInt2 + 1, 3);
    if (paramBoolean && paramad.h > 1)
      r.c(paramGraphics, paramad.h, paramInt1 + 11, paramInt2 + 2, 8); 
  }
  
  public static final void a(Graphics paramGraphics, int paramInt1, int paramInt2, ad paramad) {
    boolean bool = false;
    if (paramad instanceof e) {
      e e;
      if (!(e = (e)paramad).b) {
        paramGraphics.setColor(14663551);
        paramInt2 = (paramInt2 += bh.a(paramGraphics, paramInt1, paramInt2, 115, 1, e.a())) - bh.a() + 2;
        paramGraphics.setColor(16777215);
        bh.a(paramGraphics, paramInt1, paramInt2 + 16, 115, 1, ce.g.a(5));
      } else {
        paramGraphics.setColor(16777215);
        paramInt2 = (paramInt2 += bh.a(paramGraphics, paramInt1, paramInt2, 115, 1, e.a)) - bh.a() + 2;
        paramGraphics.setColor(14663551);
        bh.a(paramGraphics, paramInt1, paramInt2 + 25, ce.g.a((e instanceof l) ? 4 : 46), 1);
        r.c(paramGraphics, e.a, paramInt1 + 155 - 47, paramInt2 + 25, 8);
        t t;
        if (paramad instanceof t && (t = (t)paramad).c != -1) {
          paramGraphics.setColor(16711680);
          paramInt2 = (paramInt2 += bh.a(paramGraphics, paramInt1 + 55, paramInt2 + 10, 115, 1, t.a.a(t.c))) - bh.a() + 2;
        } 
        paramGraphics.setColor(14663551);
        bh.a(paramGraphics, paramInt1, paramInt2 + 40, ce.g.a(3), 1);
        r.d(paramGraphics, paramInt1 + 155 - 47, paramInt2 + 40, e.e, e.d);
        StringBuffer stringBuffer = new StringBuffer();
        for (byte b = 0; b < e.j.length; b++) {
          if (e.j[b] > 0)
            stringBuffer.append(bh.a(ce.a.a(9 + b))).append("+").append(e.j[b]).append("  "); 
        } 
        stringBuffer.append(bh.a(e.b));
        char[] arrayOfChar = null;
        arrayOfChar = stringBuffer.toString().toCharArray();
        if (r.g > 128) {
          bh.a(paramGraphics, paramInt1, paramInt2 + 55, 110, 1, arrayOfChar);
        } else {
          bh.a(paramGraphics, paramInt1, paramInt2 + 55, 75, 1, arrayOfChar);
        } 
      } 
      return;
    } 
    paramGraphics.setColor(16777215);
    paramInt2 = (paramInt2 += bh.a(paramGraphics, paramInt1, paramInt2, 115, 1, paramad.a)) - bh.a() + 2;
    paramGraphics.setColor(14663551);
    if (r.g > 128) {
      bh.a(paramGraphics, paramInt1, paramInt2 + 15, 110, 1, paramad.b);
      return;
    } 
    bh.a(paramGraphics, paramInt1, paramInt2 + 15, 75, 1, paramad.b);
  }
  
  public static final void a(Graphics paramGraphics, int paramInt1, int paramInt2, ad paramad, byte paramByte, char[] paramArrayOfchar, boolean paramBoolean) {
    b(paramGraphics, paramInt1, paramInt2 + 1, 28, 31, 12558207);
    int i = r.a(paramGraphics, ce.g.a(2), paramInt1 + 2, paramInt2 + 1);
    r.c(paramGraphics, paramByte, i + 2, paramInt2 + 1, 4);
    paramGraphics.setColor(16777215);
    bh.a(paramGraphics, paramInt1 + 90, paramInt2 + 2, paramArrayOfchar, 1);
    boolean bool = false;
    if (paramBoolean) {
      a(paramGraphics, paramInt1 + 30, paramInt2 + 14, 117, 19, 4136767, 10452799, 4144959);
      a(paramGraphics, paramInt1 + 30, paramInt2 + 14, 117, 19, 6233919);
    } else {
      a(paramGraphics, paramInt1 + 30, paramInt2 + 14, 117, 19, 6242111, 14663551, 8347519);
      a(paramGraphics, paramInt1 + 30, paramInt2 + 14, 117, 19, 10452863);
    } 
    if (paramad != null) {
      paramGraphics.drawImage(ce.d[paramad.f], paramInt1 + 14, paramInt2 + 19, 3);
      paramGraphics.setColor(16777215);
      if (paramad instanceof e && !((e)paramad).b) {
        bh.a(paramGraphics, paramInt1 + 34, paramInt2 + 20, paramad.a(), 1);
        return;
      } 
      bh.a(paramGraphics, paramInt1 + 34, paramInt2 + 20, paramad.a, 1);
    } 
  }
  
  public static final void a(Graphics paramGraphics, int paramInt1, int paramInt2, int paramInt3, char[] paramArrayOfchar, boolean paramBoolean) {
    if (paramBoolean) {
      a(paramGraphics, paramInt1, paramInt2, paramInt3, 19, 4136767, 10452799, 4144959);
      a(paramGraphics, paramInt1, paramInt2, paramInt3, 19, 6233919);
    } else {
      a(paramGraphics, paramInt1, paramInt2, paramInt3, 19, 6242111, 14663551, 8347519);
      a(paramGraphics, paramInt1, paramInt2, paramInt3, 19, 10452863);
    } 
    if (paramArrayOfchar != null) {
      paramGraphics.setColor(16777215);
      bh.a(paramGraphics, paramInt1 + paramInt3 / 2 - bh.a(paramArrayOfchar) / 2, paramInt2 + 5, paramArrayOfchar, 1);
    } 
  }
  
  public static final void a(Graphics paramGraphics, int paramInt1, int paramInt2, int paramInt3, int paramInt4, boolean paramBoolean) {
    if (paramBoolean) {
      a(paramGraphics, paramInt1, paramInt2, paramInt3, paramInt4, 6242111, 14663551, 8347519);
      return;
    } 
    a(paramGraphics, paramInt1, paramInt2, paramInt3, paramInt4, 4136767, 10452799, 4144959);
  }
  
  public static final void a(Graphics paramGraphics, int paramInt1, int paramInt2, int paramInt3, int paramInt4, char[] paramArrayOfchar, int paramInt5, int paramInt6, int paramInt7, int paramInt8) {
    paramGraphics.setColor(paramInt7);
    paramGraphics.fillRect(paramInt1, paramInt2, paramInt3, paramInt4);
    if (paramArrayOfchar == null)
      return; 
    paramInt3 = (paramInt3 -= paramInt5) - paramInt5;
    paramGraphics.setColor(paramInt8);
    if (paramInt6 == 1) {
      bh.b(paramGraphics, paramInt1 + paramInt5 + (paramInt3 >> 1), paramInt2 + 1, paramInt3, 1, paramArrayOfchar, 0, 0, paramArrayOfchar.length);
      return;
    } 
    bh.a(paramGraphics, paramInt1 + paramInt5, paramInt2 + 1, paramInt3, 1, paramArrayOfchar);
  }
  
  public static final void c(Graphics paramGraphics, int paramInt1, int paramInt2, int paramInt3, int paramInt4) {
    a(paramGraphics, paramInt1, paramInt2, paramInt3, paramInt4, 16768959, 12558207);
    c(paramGraphics, paramInt1, paramInt2, paramInt3, paramInt4, 14663551);
  }
}


/* Location:              /home/markes/Downloads/wind_of_soltia/!/cb.class
 * Java compiler version: 1 (45.3)
 * JD-Core Version:       1.1.3
 */